[
    {"name": "임구현", "alias": "헬뜨", "strong": "재밌어요", "age": "30"},
    {"name": "소리엘", "alias": "엘리소", "strong": "말수가 적음", "age": "40"},
    {"name": "배동환", "alias": "잠이 와요", "strong": "잠을 잘잠", "age": "50"},
    {"name": "이태영", "alias": "땀시만용", "strong": "메저키스트의 행복", "age": "90"},
    {"name": "최승주", "alias": "이해는 다되요", "strong": "여유는 만만하게", "age": "100"},
    {"name": "서나리", "alias": "나선생", "strong": "저 너무 잘하는것 같아요", "age": "20"},
    {"name": "임이랑", "alias": "음..저", "strong": "알고보면 잘해요", "age": "10"},
    {"name": "김하은", "alias": "수요일에 힘나요", "strong": "뭐든 크게 보여요", "age": "20"},
    {"name": "김다훈", "alias": "묵묵전진", "strong": "눈에 힘주기", "age": "40"},
    {"name": "김은주", "alias": "긍긍정적", "strong": "버그는 웃음으로 치유", "age": "20"},
    {"name": "김영훈", "alias": "수석개발자", "strong": "에러가 다 보여요", "age": "60"},
    {"name": "류정은", "alias": "GIT매니아", "strong": "아침 젤 일찍 출석", "age": "10"},
    {"name": "김아름", "alias": "코딩한아름", "strong": "그냥 다 잘해요", "age": "20"},
    {"name": "한창희", "alias": "허리펴고자기", "strong": "수동적으로 살고파요", "age": "99"},
    {"name": "김지원", "alias": "쓰러져자기", "strong": "고양이 걱정", "age": "30"},
    {"name": "박선영", "alias": "그냥웃겨요", "strong": "그냥 다 잘되요", "age": "20"},
    {"name": "백서윤", "alias": "전안웃겨요", "strong": "조용히 티 안나게", "age": "20"},
    {"name": "이다솔", "alias": "다새로워요", "strong": "노력 짱짱", "age": "20"},
    {"name": "임선영", "alias": "매직봉", "strong": "떤꽁자", "age": "20"},
    {"name": "정봉경", "alias": "유투브프리미엄", "strong": "허술반장", "age": "50"},
    {"name": "김수정", "alias": "음.말하기무서움", "strong": "체력 짱", "age": "20"},
    {"name": "정종언", "alias": "히든고수", "strong": "오타 잘내고 잘찾기", "age": "40"}
]